p360_interface_bundle/P360InterfaceBundle.py
p360_interface_bundle/P360InterfaceBundleTest.py
p360_interface_bundle/_config/config.yaml
p360_interface_bundle/_config/config_test.yaml
p360_interface_bundle/clickhouse/ClickHouseContext.py
p360_interface_bundle/clickhouse/ClickHouseQueryExecutor.py
p360_interface_bundle/clickhouse/ClickHouseTableExistenceChecker.py
p360_interface_bundle/clickhouse/ClickHouseTableUploader.py
p360_interface_bundle/clickhouse/types.py
p360_interface_bundle/export/ExportRunner.py
p360_interface_bundle/export/ExportTaskInterface.py
p360_interface_bundle/export/bins/CategoricalBinsReducer.py
p360_interface_bundle/export/bins/FloatingPointBinsGenerator.py
p360_interface_bundle/export/bins/IntegralBinsGenerator.py
p360_interface_bundle/export/tasks/BinsGenerator.py
p360_interface_bundle/export/tasks/CheckpointDirCleaner.py
p360_interface_bundle/export/tasks/CheckpointDirSetter.py
p360_interface_bundle/export/tasks/ExportCommitter.py
p360_interface_bundle/export/tasks/ExportConsistencyChecker.py
p360_interface_bundle/export/tasks/ExportTablesUploader.py
p360_interface_bundle/export/tasks/FeatureStoreLoader.py
p360_interface_bundle/export/tasks/FeatureStoreMetadataLoader.py
p360_interface_bundle/export/tasks/SampledFeatureStoreLoader.py
p360_interface_bundle/featurestore/post_actions/metadata_adjustment/CreateMetadataJsonFiles.py
p360_interface_bundle/featurestore/post_actions/metadata_adjustment/FolderContentRemover.py
p360_interface_bundle/featurestore/post_actions/metadata_adjustment/MetadataDatetimeToStringConverter.py
p360_interface_bundle/featurestore/post_actions/metadata_adjustment/MetadataDatetimeToStringConverterTest.py
p360_interface_bundle/featurestore/post_actions/metadata_adjustment/MetadataJsonGetter.py
p360_interface_bundle/featurestore/post_actions/metadata_adjustment/MetadataJsonGetterTest.py
p360_interface_bundle/featurestore/post_actions/metadata_adjustment/MetadataWriter.py
p360_interface_bundle-0.4.1.dist-info/entry_points.txt
p360_interface_bundle-0.4.1.dist-info/LICENSE
p360_interface_bundle-0.4.1.dist-info/WHEEL
p360_interface_bundle-0.4.1.dist-info/METADATA
p360_interface_bundle-0.4.1.dist-info/RECORD
