Metadata-Version: 2.1
Name: p360-interface-bundle
Version: 0.4.1
Summary: Persona360 interface bundle
License: Proprietary
Author: Datasentics
Author-email: jiri.koutny@datasentics.com
Requires-Python: >=3.8.10,<4.0.0
Classifier: License :: Other/Proprietary License
Classifier: Operating System :: OS Independent
Classifier: Programming Language :: Python :: 3
Classifier: Programming Language :: Python :: 3.9
Requires-Dist: daipe-core (>=1.4.2,<2.0.0)
Requires-Dist: databricks-bundle (>=1.4.5,<2.0.0)
Requires-Dist: feature-store-bundle (>=2.9,<3.0)
Requires-Dist: pyfony-bundles (>=0.4.4,<0.5.0)
Requires-Dist: requests (>=2.25.0,<3.0.0)
